lrctoolbox/__init__.py
lrctoolbox/exceptions.py
lrctoolbox/lrc_metadata.py
lrctoolbox/py.typed
lrctoolbox/synced_lyric_line.py
lrctoolbox/synced_lyrics.py
lrctoolbox-1.2.0.dist-info/METADATA
lrctoolbox-1.2.0.dist-info/WHEEL
lrctoolbox-1.2.0.dist-info/RECORD
