Metadata-Version: 2.1
Name: lrctoolbox
Version: 1.2.0
Summary: toolkit for working with lrc files
Home-page: https://github.com/Dr-Blank/lrctoolbox
License: GPL-3.0-or-later
Keywords: lrc,lyrics,pylrc,synced lyrics,karaoke,music,file,parser,editor,converter
Author: Dr-Blank
Author-email: 64108942+Dr-Blank@users.noreply.github.com
Requires-Python: >=3.10,<4.0
Classifier: Development Status :: 4 - Beta
Classifier: Intended Audience :: Developers
Classifier: License :: OSI Approved :: GNU General Public License v3 or later (GPLv3+)
Classifier: Programming Language :: Python
Classifier: Programming Language :: Python :: 3
Classifier: Programming Language :: Python :: 3.10
Classifier: Programming Language :: Python :: 3.11
Classifier: Programming Language :: Python :: 3.12
Classifier: Topic :: Desktop Environment :: File Managers
Classifier: Topic :: Multimedia :: Sound/Audio
Classifier: Topic :: Software Development :: Libraries :: Python Modules
Classifier: Topic :: Text Processing
Classifier: Topic :: Utilities
Project-URL: Repository, https://github.com/Dr-Blank/lrctoolbox
